vacuum_map_parser_dreame/__init__.py
vacuum_map_parser_dreame/header.py
vacuum_map_parser_dreame/image_parser.py
vacuum_map_parser_dreame/map_data_parser.py
vacuum_map_parser_dreame/map_data_type.py
vacuum_map_parser_dreame/py.typed
vacuum_map_parser_dreame-0.1.3.dist-info/LICENSE
vacuum_map_parser_dreame-0.1.3.dist-info/METADATA
vacuum_map_parser_dreame-0.1.3.dist-info/WHEEL
vacuum_map_parser_dreame-0.1.3.dist-info/RECORD
