Metadata-Version: 2.1
Name: vacuum-map-parser-dreame
Version: 0.1.3
Summary: Functionalities for Dreame vacuum map parsing
License: Apache-2.0
Author: Piotr Machowski
Author-email: piotr.machowski.dev@gmail.com
Requires-Python: >=3.11,<4.0
Classifier: Development Status :: 4 - Beta
Classifier: Environment :: Console
Classifier: Intended Audience :: Developers
Classifier: License :: OSI Approved :: Apache Software License
Classifier: Programming Language :: Python :: 3
Classifier: Programming Language :: Python :: 3.11
Classifier: Topic :: Home Automation
Requires-Dist: Pillow
Requires-Dist: pycryptodome
Requires-Dist: vacuum-map-parser-base (==0.1.5)
Project-URL: Bug Tracker, https://github.com/PiotrMachowski/Python-package-vacuum-map-parser-dreame/issues
Project-URL: Changelog, https://github.com/PiotrMachowski/Python-package-vacuum-map-parser-dreame/releases
Project-URL: Homepage, https://github.com/PiotrMachowski/Python-package-vacuum-map-parser-dreame
Project-URL: Repository, https://github.com/PiotrMachowski/Python-package-vacuum-map-parser-dreame
